README.md
setup.py
src/MicroPyDD_restplus.egg-info/PKG-INFO
src/MicroPyDD_restplus.egg-info/SOURCES.txt
src/MicroPyDD_restplus.egg-info/dependency_links.txt
src/MicroPyDD_restplus.egg-info/requires.txt
src/MicroPyDD_restplus.egg-info/top_level.txt
src/micropydd_restplus/__init__.py
src/micropydd_restplus/actions.py
src/micropydd_restplus/config.py
src/micropydd_restplus/decorators.py
src/micropydd_restplus/module.py
src/micropydd_restplus/rest.py
src/micropydd_restplus/utils.py
src/micropydd_restplus/namespaces/__init__.py
src/micropydd_restplus/namespaces/logger.py
src/micropydd_restplus/namespaces/misc.py