Metadata-Version: 2.1
Name: MicroPyDD-restplus
Version: 0.0.6
Summary: MicroPyDD wrapper for Flask-Restplus
Home-page: UNKNOWN
Author: Danilo Delizia
Author-email: ddelizia@gmail.com
License: UNKNOWN
Platform: UNKNOWN
